{
    "swagger": "2.0",
    "info": {
        "description": "This is a sample rest api realized in go language for education purposes.",
        "title": "Go REST API example",
        "contact": {
            "email": "artyom.nikolaev@syahoo.com"
        },
        "version": "2.0"
    },
    "host": "localhost:8000",
    "basePath": "/api/v2",
    "paths": {
        "/comment/{id}": {
            "get": {
                "description": "Gets comment record from database using provided id.",
                "produces": [
                    "application/json",
                    "text/xml"
                ],
                "summary": "Gets comment record.",
                "operationId": "GetComment",
                "responses": {
                    "200": {
                        "description": "OK",
                        "schema": {
                            "$ref": "#/definitions/GetCommentResponse"
                        }
                    },
                    "400": {
                        "description": "Bad Request",
                        "schema": {
                            "$ref": "#/definitions/GetCommentResponse"
                        }
                    },
                    "404": {
                        "description": "Bad Request",
                        "schema": {
                            "$ref": "#/definitions/GetCommentResponse"
                        }
                    },
                    "500": {
                        "description": "Internal Server Error",
                        "schema": {
                            "$ref": "#/definitions/GetCommentResponse"
                        }
                    },
                    "default": {
                        "description": "",
                        "schema": {
                            "$ref": "#/definitions/GetCommentResponse"
                        }
                    }
                }
            }
        },
        "/comments": {
            "get": {
                "description": "Gets comment records from database using provided query.",
                "produces": [
                    "application/json",
                    "text/xml"
                ],
                "summary": "Gets comment records.",
                "operationId": "GetComments",
                "parameters": [
                    {
                        "type": "integer",
                        "name": "limit",
                        "in": "query"
                    },
                    {
                        "type": "integer",
                        "name": "offset",
                        "in": "query"
                    },
                    {
                        "type": "string",
                        "name": "postID",
                        "in": "query"
                    },
                    {
                        "type": "string",
                        "name": "userID",
                        "in": "query"
                    }
                ],
                "responses": {
                    "200": {
                        "description": "OK",
                        "schema": {
                            "$ref": "#/definitions/GetCommentsResponse"
                        }
                    },
                    "400": {
                        "description": "Bad Request",
                        "schema": {
                            "$ref": "#/definitions/GetCommentsResponse"
                        }
                    },
                    "404": {
                        "description": "Bad Request",
                        "schema": {
                            "$ref": "#/definitions/GetCommentsResponse"
                        }
                    },
                    "500": {
                        "description": "Internal Server Error",
                        "schema": {
                            "$ref": "#/definitions/GetCommentsResponse"
                        }
                    },
                    "default": {
                        "description": "",
                        "schema": {
                            "$ref": "#/definitions/GetCommentsResponse"
                        }
                    }
                }
            },
            "post": {
                "description": "Creates comment record in database using provided data.",
                "consumes": [
                    "application/json"
                ],
                "produces": [
                    "application/json",
                    "text/xml"
                ],
                "summary": "Creates comment record.",
                "operationId": "CreateComment",
                "parameters": [
                    {
                        "description": "data",
                        "name": "fields",
                        "in": "body",
                        "required": true,
                        "schema": {
                            "$ref": "#/definitions/CreateCommentRequest"
                        }
                    }
                ],
                "responses": {
                    "200": {
                        "description": "OK",
                        "schema": {
                            "$ref": "#/definitions/CreateCommentResponse"
                        }
                    },
                    "400": {
                        "description": "Bad Request",
                        "schema": {
                            "$ref": "#/definitions/CreateCommentResponse"
                        }
                    },
                    "404": {
                        "description": "Bad Request",
                        "schema": {
                            "$ref": "#/definitions/CreateCommentResponse"
                        }
                    },
                    "500": {
                        "description": "Internal Server Error",
                        "schema": {
                            "$ref": "#/definitions/CreateCommentResponse"
                        }
                    },
                    "default": {
                        "description": "",
                        "schema": {
                            "$ref": "#/definitions/CreateCommentResponse"
                        }
                    }
                }
            }
        },
        "/comments/{id}": {
            "delete": {
                "description": "Deletes comment record from database using provided id.",
                "produces": [
                    "application/json",
                    "text/xml"
                ],
                "summary": "Deletes comment record.",
                "operationId": "DeleteComment",
                "responses": {
                    "200": {
                        "description": "OK",
                        "schema": {
                            "$ref": "#/definitions/DeleteCommentResponse"
                        }
                    },
                    "400": {
                        "description": "Bad Request",
                        "schema": {
                            "$ref": "#/definitions/DeleteCommentResponse"
                        }
                    },
                    "404": {
                        "description": "Bad Request",
                        "schema": {
                            "$ref": "#/definitions/DeleteCommentResponse"
                        }
                    },
                    "500": {
                        "description": "Internal Server Error",
                        "schema": {
                            "$ref": "#/definitions/DeleteCommentResponse"
                        }
                    },
                    "default": {
                        "description": "",
                        "schema": {
                            "$ref": "#/definitions/DeleteCommentResponse"
                        }
                    }
                }
            }
        },
        "/posts": {
            "get": {
                "description": "Gets post records from database using provided query.",
                "produces": [
                    "application/json",
                    "text/xml"
                ],
                "summary": "Gets post records.",
                "operationId": "GetPosts",
                "parameters": [
                    {
                        "type": "integer",
                        "name": "limit",
                        "in": "query"
                    },
                    {
                        "type": "integer",
                        "name": "offset",
                        "in": "query"
                    }
                ],
                "responses": {
                    "200": {
                        "description": "OK",
                        "schema": {
                            "$ref": "#/definitions/github.com_Tamplier2911_gorest_core_posts.GetPostResponse"
                        }
                    },
                    "400": {
                        "description": "Bad Request",
                        "schema": {
                            "$ref": "#/definitions/github.com_Tamplier2911_gorest_core_posts.GetPostResponse"
                        }
                    },
                    "404": {
                        "description": "Bad Request",
                        "schema": {
                            "$ref": "#/definitions/github.com_Tamplier2911_gorest_core_posts.GetPostResponse"
                        }
                    },
                    "500": {
                        "description": "Internal Server Error",
                        "schema": {
                            "$ref": "#/definitions/github.com_Tamplier2911_gorest_core_posts.GetPostResponse"
                        }
                    },
                    "default": {
                        "description": "",
                        "schema": {
                            "$ref": "#/definitions/github.com_Tamplier2911_gorest_core_posts.GetPostResponse"
                        }
                    }
                }
            },
            "post": {
                "description": "Creates post record in database using provided data.",
                "consumes": [
                    "application/json"
                ],
                "produces": [
                    "application/json",
                    "text/xml"
                ],
                "summary": "Creates post record.",
                "operationId": "CreatePost",
                "parameters": [
                    {
                        "description": "data",
                        "name": "fields",
                        "in": "body",
                        "required": true,
                        "schema": {
                            "$ref": "#/definitions/CreatePostRequest"
                        }
                    }
                ],
                "responses": {
                    "200": {
                        "description": "OK",
                        "schema": {
                            "$ref": "#/definitions/CreatePostResponse"
                        }
                    },
                    "400": {
                        "description": "Bad Request",
                        "schema": {
                            "$ref": "#/definitions/CreatePostResponse"
                        }
                    },
                    "404": {
                        "description": "Bad Request",
                        "schema": {
                            "$ref": "#/definitions/CreatePostResponse"
                        }
                    },
                    "500": {
                        "description": "Internal Server Error",
                        "schema": {
                            "$ref": "#/definitions/CreatePostResponse"
                        }
                    },
                    "default": {
                        "description": "",
                        "schema": {
                            "$ref": "#/definitions/CreatePostResponse"
                        }
                    }
                }
            }
        },
        "/posts/{id}": {
            "get": {
                "description": "Gets post record from database using provided id.",
                "produces": [
                    "application/json",
                    "text/xml"
                ],
                "summary": "Gets post record.",
                "operationId": "GetPost",
                "responses": {
                    "200": {
                        "description": "OK",
                        "schema": {
                            "$ref": "#/definitions/github.com_Tamplier2911_gorest_core_posts.GetPostResponse"
                        }
                    },
                    "400": {
                        "description": "Bad Request",
                        "schema": {
                            "$ref": "#/definitions/github.com_Tamplier2911_gorest_core_posts.GetPostResponse"
                        }
                    },
                    "404": {
                        "description": "Bad Request",
                        "schema": {
                            "$ref": "#/definitions/github.com_Tamplier2911_gorest_core_posts.GetPostResponse"
                        }
                    },
                    "500": {
                        "description": "Internal Server Error",
                        "schema": {
                            "$ref": "#/definitions/github.com_Tamplier2911_gorest_core_posts.GetPostResponse"
                        }
                    },
                    "default": {
                        "description": "",
                        "schema": {
                            "$ref": "#/definitions/github.com_Tamplier2911_gorest_core_posts.GetPostResponse"
                        }
                    }
                }
            },
            "put": {
                "description": "Updates comment record in database using provided data.",
                "consumes": [
                    "application/json"
                ],
                "produces": [
                    "application/json",
                    "text/xml"
                ],
                "summary": "Updates comment record.",
                "operationId": "UpdateComment",
                "parameters": [
                    {
                        "description": "data",
                        "name": "fields",
                        "in": "body",
                        "required": true,
                        "schema": {
                            "$ref": "#/definitions/UpdateCommentRequest"
                        }
                    }
                ],
                "responses": {
                    "200": {
                        "description": "OK",
                        "schema": {
                            "$ref": "#/definitions/UpdateCommentResponse"
                        }
                    },
                    "400": {
                        "description": "Bad Request",
                        "schema": {
                            "$ref": "#/definitions/UpdateCommentResponse"
                        }
                    },
                    "404": {
                        "description": "Bad Request",
                        "schema": {
                            "$ref": "#/definitions/UpdateCommentResponse"
                        }
                    },
                    "500": {
                        "description": "Internal Server Error",
                        "schema": {
                            "$ref": "#/definitions/UpdateCommentResponse"
                        }
                    },
                    "default": {
                        "description": "",
                        "schema": {
                            "$ref": "#/definitions/UpdateCommentResponse"
                        }
                    }
                }
            },
            "delete": {
                "description": "Deletes post record from database using provided id.",
                "produces": [
                    "application/json",
                    "text/xml"
                ],
                "summary": "Deletes post record.",
                "operationId": "DeletePost",
                "responses": {
                    "200": {
                        "description": "OK",
                        "schema": {
                            "$ref": "#/definitions/DeletePostResponse"
                        }
                    },
                    "400": {
                        "description": "Bad Request",
                        "schema": {
                            "$ref": "#/definitions/DeletePostResponse"
                        }
                    },
                    "404": {
                        "description": "Bad Request",
                        "schema": {
                            "$ref": "#/definitions/DeletePostResponse"
                        }
                    },
                    "500": {
                        "description": "Internal Server Error",
                        "schema": {
                            "$ref": "#/definitions/DeletePostResponse"
                        }
                    },
                    "default": {
                        "description": "",
                        "schema": {
                            "$ref": "#/definitions/DeletePostResponse"
                        }
                    }
                }
            }
        }
    },
    "definitions": {
        "CreateCommentRequest": {
            "type": "object",
            "required": [
                "body",
                "name",
                "postId",
                "userId"
            ],
            "properties": {
                "body": {
                    "type": "string"
                },
                "name": {
                    "type": "string"
                },
                "postId": {
                    "type": "string"
                },
                "userId": {
                    "type": "string"
                }
            }
        },
        "CreateCommentResponse": {
            "type": "object",
            "properties": {
                "comment": {
                    "$ref": "#/definitions/models.Comment"
                },
                "message": {
                    "type": "string"
                }
            }
        },
        "CreatePostRequest": {
            "type": "object",
            "required": [
                "body",
                "title",
                "userId"
            ],
            "properties": {
                "body": {
                    "type": "string"
                },
                "title": {
                    "type": "string"
                },
                "userId": {
                    "type": "string"
                }
            }
        },
        "CreatePostResponse": {
            "type": "object",
            "properties": {
                "message": {
                    "type": "string"
                },
                "post": {
                    "$ref": "#/definitions/models.Post"
                }
            }
        },
        "DeleteCommentResponse": {
            "type": "object",
            "properties": {
                "message": {
                    "type": "string"
                }
            }
        },
        "DeletePostResponse": {
            "type": "object",
            "properties": {
                "message": {
                    "type": "string"
                }
            }
        },
        "GetCommentResponse": {
            "type": "object",
            "properties": {
                "comment": {
                    "$ref": "#/definitions/models.Comment"
                },
                "message": {
                    "type": "string"
                }
            }
        },
        "GetCommentsResponse": {
            "type": "object",
            "properties": {
                "comments": {
                    "type": "array",
                    "items": {
                        "$ref": "#/definitions/models.Comment"
                    }
                },
                "message": {
                    "type": "string"
                },
                "total": {
                    "type": "integer"
                }
            }
        },
        "UpdateCommentRequest": {
            "type": "object",
            "required": [
                "body",
                "name"
            ],
            "properties": {
                "body": {
                    "type": "string"
                },
                "name": {
                    "type": "string"
                }
            }
        },
        "UpdateCommentResponse": {
            "type": "object",
            "properties": {
                "message": {
                    "type": "string"
                }
            }
        },
        "UpdatePostRequest": {
            "type": "object",
            "required": [
                "body",
                "title"
            ],
            "properties": {
                "body": {
                    "type": "string"
                },
                "title": {
                    "type": "string"
                }
            }
        },
        "UpdatePostResponse": {
            "type": "object",
            "properties": {
                "message": {
                    "type": "string"
                }
            }
        },
        "github.com_Tamplier2911_gorest_core_posts.GetPostResponse": {
            "type": "object",
            "properties": {
                "message": {
                    "type": "string"
                },
                "post": {
                    "$ref": "#/definitions/models.Post"
                }
            }
        },
        "models.Comment": {
            "type": "object",
            "properties": {
                "body": {
                    "type": "string"
                },
                "id": {
                    "type": "string"
                },
                "name": {
                    "type": "string"
                },
                "postId": {
                    "type": "string"
                },
                "userId": {
                    "type": "string"
                }
            }
        },
        "models.Post": {
            "type": "object",
            "properties": {
                "body": {
                    "type": "string"
                },
                "id": {
                    "type": "string"
                },
                "title": {
                    "type": "string"
                },
                "userId": {
                    "type": "string"
                }
            }
        }
    }
}